Metadata-Version: 1.0
Name: liac-arff
Version: 1.0
Summary: A library for read and write ARFF files in Python
Home-page: http://inf.ufrgs.br/~rppereira
Author: Renato de Pontes Pereira
Author-email: renato.ppontes@gmail.com
License: MIT License
Download-URL: https://github.com/renatopp/liac-arff
Keywords: arff weka parser liac python
Platform: UNKNOWN
Classifier: Development Status :: 5 - Production/Stable
Classifier: Environment :: MacOS X
Classifier: Environment :: Win32 (MS Windows)
Classifier: Environment :: X11 Applications
Classifier: Intended Audience :: Developers
Classifier: License :: OSI Approved :: MIT License
Classifier: Natural Language :: English
Classifier: Operating System :: MacOS :: MacOS X
Classifier: Operating System :: Microsoft :: Windows
Classifier: Operating System :: POSIX :: Linux
Classifier: Programming Language :: Python
Classifier: Topic :: Software Development :: Libraries :: Python Modules
Classifier: Topic :: Scientific/Engineering :: Artificial Intelligence
